[
    {
        "title": "Curriculum",
        "link" :  "https://github.com/ale70029/ngPortfolio/raw/bd5a3099c48e08d14810d49abf7dd660e3c697fb/public/data/CV%20Alessandro%20Ciccarone.pdf",
        "icon": "assets/contacts/cv.png"
    },
    {
        "title": "Github",
        "link" :  "https://github.com/ale70029",
        "icon": "assets/contacts/githubIcon.png"
    },
    {
        "title": "Linkedin",
        "link" :  "https://www.linkedin.com/in/alessandro-ciccarone/",
        "icon": "assets/contacts/linkedinIcon.png"
    },
    {
        "title": "Linkedin",
        "link" :  "mailto:alessandro.ciccarone1994@gmail.com",
        "icon": "assets/contacts/emailIcon.png"
    }
]
